alibabacloud_dataphin_public20230630/__init__.py
alibabacloud_dataphin_public20230630/client.py
alibabacloud_dataphin_public20230630/models/__init__.py
alibabacloud_dataphin_public20230630/models/_add_data_service_project_member_request.py
alibabacloud_dataphin_public20230630/models/_add_data_service_project_member_response.py
alibabacloud_dataphin_public20230630/models/_add_data_service_project_member_response_body.py
alibabacloud_dataphin_public20230630/models/_add_data_service_project_member_shrink_request.py
alibabacloud_dataphin_public20230630/models/_add_project_member_request.py
alibabacloud_dataphin_public20230630/models/_add_project_member_response.py
alibabacloud_dataphin_public20230630/models/_add_project_member_response_body.py
alibabacloud_dataphin_public20230630/models/_add_project_member_shrink_request.py
alibabacloud_dataphin_public20230630/models/_add_register_lineage_request.py
alibabacloud_dataphin_public20230630/models/_add_register_lineage_response.py
alibabacloud_dataphin_public20230630/models/_add_register_lineage_response_body.py
alibabacloud_dataphin_public20230630/models/_add_register_lineage_shrink_request.py
alibabacloud_dataphin_public20230630/models/_add_tenant_members_by_source_user_request.py
alibabacloud_dataphin_public20230630/models/_add_tenant_members_by_source_user_response.py
alibabacloud_dataphin_public20230630/models/_add_tenant_members_by_source_user_response_body.py
alibabacloud_dataphin_public20230630/models/_add_tenant_members_by_source_user_shrink_request.py
alibabacloud_dataphin_public20230630/models/_add_tenant_members_request.py
alibabacloud_dataphin_public20230630/models/_add_tenant_members_response.py
alibabacloud_dataphin_public20230630/models/_add_tenant_members_response_body.py
alibabacloud_dataphin_public20230630/models/_add_tenant_members_shrink_request.py
alibabacloud_dataphin_public20230630/models/_add_user_group_member_request.py
alibabacloud_dataphin_public20230630/models/_add_user_group_member_response.py
alibabacloud_dataphin_public20230630-2.4.0.dist-info/LICENSE
alibabacloud_dataphin_public20230630-2.4.0.dist-info/METADATA
alibabacloud_dataphin_public20230630-2.4.0.dist-info/WHEEL
alibabacloud_dataphin_public20230630-2.4.0.dist-info/top_level.txt
alibabacloud_dataphin_public20230630-2.4.0.dist-info/RECORD
